ndx_zebrafish/__init__.py
ndx_zebrafish/spec/ndx-zebrafish.extensions.yaml
ndx_zebrafish/spec/ndx-zebrafish.namespace.yaml
ndx_zebrafish-0.1.0.dist-info/LICENSE.txt
ndx_zebrafish-0.1.0.dist-info/METADATA
ndx_zebrafish-0.1.0.dist-info/WHEEL
ndx_zebrafish-0.1.0.dist-info/top_level.txt
ndx_zebrafish-0.1.0.dist-info/RECORD
