Metadata-Version: 2.1
Name: ndx-zebrafish
Version: 0.1.0
Summary: NWB extensions for storing (larval) zebrafish expreiment related data
Home-page: 
Author: Ruben Portugues, Martin Haesemeyer, Luigi Petrucco, Vilim Stih
Author-email: ruben.portugues@tum.de
License: MIT
Keywords: NeurodataWithoutBorders,NWB,nwb-extension,ndx-extension
Classifier: Intended Audience :: Developers
Classifier: Intended Audience :: Science/Research
Classifier: License :: OSI Approved :: MIT License
License-File: LICENSE.txt
Requires-Dist: pynwb (<3,>=1.5.0)
Requires-Dist: hdmf (<4,>=2.5.6)
Requires-Dist: hdmf-docutils (<1,>=0.4.4)
